{"id":392,"genderRate":1,"captureRate":45,"baseHappiness":70,"legendary":false,"mythical":false,"abilities":[{"hidden":false,"id":66},{"hidden":true,"id":89}],"stats":[{"id":1,"base":76,"effort":0},{"id":2,"base":104,"effort":1},{"id":3,"base":71,"effort":0},{"id":4,"base":104,"effort":1},{"id":5,"base":71,"effort":0},{"id":6,"base":108,"effort":1}],"moves":[{"generation":4,"learn_method_id":1,"level":1,"move_id":10},{"generation":4,"learn_method_id":4,"level":0,"move_id":14},{"generation":4,"learn_method_id":4,"level":0,"move_id":15},{"generation":4,"learn_method_id":1,"level":1,"move_id":43},{"generation":4,"learn_method_id":4,"level":0,"move_id":46},{"generation":4,"learn_method_id":1,"level":1,"move_id":52},{"generation":4,"learn_method_id":1,"level":7,"move_id":52},{"generation":4,"learn_method_id":4,"level":0,"move_id":53},{"generation":4,"learn_method_id":4,"level":0,"move_id":63},{"generation":4,"learn_method_id":4,"level":0,"move_id":70},{"generation":4,"learn_method_id":4,"level":0,"move_id":76},{"generation":4,"learn_method_id":1,"level":45,"move_id":83},{"generation":4,"learn_method_id":4,"level":0,"move_id":89},{"generation":4,"learn_method_id":4,"level":0,"move_id":91},{"generation":4,"learn_method_id":4,"level":0,"move_id":92},{"generation":4,"learn_method_id":4,"level":0,"move_id":104},{"generation":4,"learn_method_id":4,"level":0,"move_id":126},{"generation":4,"learn_method_id":1,"level":17,"move_id":154},{"generation":4,"learn_method_id":4,"level":0,"move_id":156},{"generation":4,"learn_method_id":4,"level":0,"move_id":157},{"generation":4,"learn_method_id":4,"level":0,"move_id":164},{"generation":4,"learn_method_id":1,"level":21,"move_id":172},{"generation":4,"learn_method_id":4,"level":0,"move_id":182},{"generation":4,"learn_method_id":1,"level":14,"move_id":183},{"generation":4,"learn_method_id":4,"level":0,"move_id":203},{"generation":4,"learn_method_id":4,"level":0,"move_id":207},{"generation":4,"learn_method_id":4,"level":0,"move_id":213},{"generation":4,"learn_method_id":4,"level":0,"move_id":214},{"generation":4,"learn_method_id":4,"level":0,"move_id":216},{"generation":4,"learn_method_id":4,"level":0,"move_id":218},{"generation":4,"learn_method_id":4,"level":0,"move_id":231},{"generation":4,"learn_method_id":4,"level":0,"move_id":237},{"generation":4,"learn_method_id":4,"level":0,"move_id":241},{"generation":4,"learn_method_id":4,"level":0,"move_id":249},{"generation":4,"learn_method_id":4,"level":0,"move_id":259},{"generation":4,"learn_method_id":4,"level":0,"move_id":261},{"generation":4,"learn_method_id":4,"level":0,"move_id":263},{"generation":4,"learn_method_id":4,"level":0,"move_id":264},{"generation":4,"learn_method_id":1,"level":1,"move_id":269},{"generation":4,"learn_method_id":1,"level":9,"move_id":269},{"generation":4,"learn_method_id":4,"level":0,"move_id":269},{"generation":4,"learn_method_id":4,"level":0,"move_id":280},{"generation":4,"learn_method_id":4,"level":0,"move_id":290},{"generation":4,"learn_method_id":3,"level":0,"move_id":307},{"generation":4,"learn_method_id":4,"level":0,"move_id":315},{"generation":4,"learn_method_id":4,"level":0,"move_id":317},{"generation":4,"learn_method_id":4,"level":0,"move_id":332},{"generation":4,"learn_method_id":4,"level":0,"move_id":339},{"generation":4,"learn_method_id":1,"level":53,"move_id":347},{"generation":4,"learn_method_id":4,"level":0,"move_id":347},{"generation":4,"learn_method_id":4,"level":0,"move_id":363},{"generation":4,"learn_method_id":1,"level":29,"move_id":364},{"generation":4,"learn_method_id":4,"level":0,"move_id":369},{"generation":4,"learn_method_id":1,"level":41,"move_id":370},{"generation":4,"learn_method_id":4,"level":0,"move_id":374},{"generation":4,"learn_method_id":1,"level":33,"move_id":386},{"generation":4,"learn_method_id":1,"level":57,"move_id":394},{"generation":4,"learn_method_id":4,"level":0,"move_id":398},{"generation":4,"learn_method_id":4,"level":0,"move_id":411},{"generation":4,"learn_method_id":4,"level":0,"move_id":416},{"generation":4,"learn_method_id":4,"level":0,"move_id":421},{"generation":4,"learn_method_id":4,"level":0,"move_id":431},{"generation":4,"learn_method_id":4,"level":0,"move_id":444},{"generation":4,"learn_method_id":4,"level":0,"move_id":445},{"generation":4,"learn_method_id":4,"level":0,"move_id":446},{"generation":4,"learn_method_id":4,"level":0,"move_id":447},{"generation":4,"learn_method_id":3,"level":0,"move_id":7},{"generation":4,"learn_method_id":3,"level":0,"move_id":9},{"generation":4,"learn_method_id":1,"level":1,"move_id":10},{"generation":4,"learn_method_id":4,"level":0,"move_id":14},{"generation":4,"learn_method_id":4,"level":0,"move_id":15},{"generation":4,"learn_method_id":1,"level":1,"move_id":43},{"generation":4,"learn_method_id":4,"level":0,"move_id":46},{"generation":4,"learn_method_id":1,"level":1,"move_id":52},{"generation":4,"learn_method_id":1,"level":7,"move_id":52},{"generation":4,"learn_method_id":4,"level":0,"move_id":53},{"generation":4,"learn_method_id":4,"level":0,"move_id":63},{"generation":4,"learn_method_id":4,"level":0,"move_id":70},{"generation":4,"learn_method_id":4,"level":0,"move_id":76},{"generation":4,"learn_method_id":1,"level":45,"move_id":83},{"generation":4,"learn_method_id":4,"level":0,"move_id":89},{"generation":4,"learn_method_id":4,"level":0,"move_id":91},{"generation":4,"learn_method_id":4,"level":0,"move_id":92},{"generation":4,"learn_method_id":4,"level":0,"move_id":104},{"generation":4,"learn_method_id":4,"level":0,"move_id":126},{"generation":4,"learn_method_id":3,"level":0,"move_id":129},{"generation":4,"learn_method_id":1,"level":17,"move_id":154},{"generation":4,"learn_method_id":4,"level":0,"move_id":156},{"generation":4,"learn_method_id":4,"level":0,"move_id":157},{"generation":4,"learn_method_id":4,"level":0,"move_id":164},{"generation":4,"learn_method_id":1,"level":21,"move_id":172},{"generation":4,"learn_method_id":3,"level":0,"move_id":173},{"generation":4,"learn_method_id":4,"level":0,"move_id":182},{"generation":4,"learn_method_id":1,"level":14,"move_id":183},{"generation":4,"learn_method_id":3,"level":0,"move_id":189},{"generation":4,"learn_method_id":4,"level":0,"move_id":203},{"generation":4,"learn_method_id":3,"level":0,"move_id":205},{"generation":4,"learn_method_id":4,"level":0,"move_id":207},{"generation":4,"learn_method_id":4,"level":0,"move_id":213},{"generation":4,"learn_method_id":4,"level":0,"move_id":214},{"generation":4,"learn_method_id":4,"level":0,"move_id":216},{"generation":4,"learn_method_id":4,"level":0,"move_id":218},{"generation":4,"learn_method_id":4,"level":0,"move_id":231},{"generation":4,"learn_method_id":4,"level":0,"move_id":237},{"generation":4,"learn_method_id":4,"level":0,"move_id":241},{"generation":4,"learn_method_id":4,"level":0,"move_id":249},{"generation":4,"learn_method_id":3,"level":0,"move_id":257},{"generation":4,"learn_method_id":4,"level":0,"move_id":259},{"generation":4,"learn_method_id":4,"level":0,"move_id":261},{"generation":4,"learn_method_id":4,"level":0,"move_id":263},{"generation":4,"learn_method_id":4,"level":0,"move_id":264},{"generation":4,"learn_method_id":1,"level":1,"move_id":269},{"generation":4,"learn_method_id":1,"level":9,"move_id":269},{"generation":4,"learn_method_id":4,"level":0,"move_id":269},{"generation":4,"learn_method_id":3,"level":0,"move_id":270},{"generation":4,"learn_method_id":4,"level":0,"move_id":280},{"generation":4,"learn_method_id":3,"level":0,"move_id":283},{"generation":4,"learn_method_id":4,"level":0,"move_id":290},{"generation":4,"learn_method_id":3,"level":0,"move_id":307},{"generation":4,"learn_method_id":4,"level":0,"move_id":315},{"generation":4,"learn_method_id":4,"level":0,"move_id":317},{"generation":4,"learn_method_id":4,"level":0,"move_id":332},{"generation":4,"learn_method_id":4,"level":0,"move_id":339},{"generation":4,"learn_method_id":1,"level":53,"move_id":347},{"generation":4,"learn_method_id":4,"level":0,"move_id":347},{"generation":4,"learn_method_id":4,"level":0,"move_id":363},{"generation":4,"learn_method_id":1,"level":29,"move_id":364},{"generation":4,"learn_method_id":4,"level":0,"move_id":369},{"generation":4,"learn_method_id":1,"level":41,"move_id":370},{"generation":4,"learn_method_id":4,"level":0,"move_id":374},{"generation":4,"learn_method_id":1,"level":33,"move_id":386},{"generation":4,"learn_method_id":1,"level":57,"move_id":394},{"generation":4,"learn_method_id":4,"level":0,"move_id":398},{"generation":4,"learn_method_id":3,"level":0,"move_id":410},{"generation":4,"learn_method_id":4,"level":0,"move_id":411},{"generation":4,"learn_method_id":4,"level":0,"move_id":416},{"generation":4,"learn_method_id":4,"level":0,"move_id":421},{"generation":4,"learn_method_id":4,"level":0,"move_id":431},{"generation":4,"learn_method_id":3,"level":0,"move_id":441},{"generation":4,"learn_method_id":4,"level":0,"move_id":444},{"generation":4,"learn_method_id":4,"level":0,"move_id":445},{"generation":4,"learn_method_id":4,"level":0,"move_id":446},{"generation":4,"learn_method_id":4,"level":0,"move_id":447},{"generation":4,"learn_method_id":3,"level":0,"move_id":7},{"generation":4,"learn_method_id":3,"level":0,"move_id":9},{"generation":4,"learn_method_id":1,"level":1,"move_id":10},{"generation":4,"learn_method_id":4,"level":0,"move_id":14},{"generation":4,"learn_method_id":4,"level":0,"move_id":15},{"generation":4,"learn_method_id":3,"level":0,"move_id":29},{"generation":4,"learn_method_id":1,"level":1,"move_id":43},{"generation":4,"learn_method_id":4,"level":0,"move_id":46},{"generation":4,"learn_method_id":1,"level":1,"move_id":52},{"generation":4,"learn_method_id":1,"level":7,"move_id":52},{"generation":4,"learn_method_id":4,"level":0,"move_id":53},{"generation":4,"learn_method_id":4,"level":0,"move_id":63},{"generation":4,"learn_method_id":3,"level":0,"move_id":67},{"generation":4,"learn_method_id":4,"level":0,"move_id":70},{"generation":4,"learn_method_id":4,"level":0,"move_id":76},{"generation":4,"learn_method_id":1,"level":45,"move_id":83},{"generation":4,"learn_method_id":4,"level":0,"move_id":89},{"generation":4,"learn_method_id":4,"level":0,"move_id":91},{"generation":4,"learn_method_id":4,"level":0,"move_id":92},{"generation":4,"learn_method_id":4,"level":0,"move_id":104},{"generation":4,"learn_method_id":4,"level":0,"move_id":126},{"generation":4,"learn_method_id":3,"level":0,"move_id":129},{"generation":4,"learn_method_id":1,"level":17,"move_id":154},{"generation":4,"learn_method_id":4,"level":0,"move_id":156},{"generation":4,"learn_method_id":4,"level":0,"move_id":157},{"generation":4,"learn_method_id":4,"level":0,"move_id":164},{"generation":4,"learn_method_id":1,"level":21,"move_id":172},{"generation":4,"learn_method_id":3,"level":0,"move_id":173},{"generation":4,"learn_method_id":4,"level":0,"move_id":182},{"generation":4,"learn_method_id":1,"level":14,"move_id":183},{"generation":4,"learn_method_id":3,"level":0,"move_id":189},{"generation":4,"learn_method_id":4,"level":0,"move_id":203},{"generation":4,"learn_method_id":3,"level":0,"move_id":205},{"generation":4,"learn_method_id":4,"level":0,"move_id":207},{"generation":4,"learn_method_id":4,"level":0,"move_id":213},{"generation":4,"learn_method_id":4,"level":0,"move_id":214},{"generation":4,"learn_method_id":4,"level":0,"move_id":216},{"generation":4,"learn_method_id":4,"level":0,"move_id":218},{"generation":4,"learn_method_id":4,"level":0,"move_id":231},{"generation":4,"learn_method_id":4,"level":0,"move_id":237},{"generation":4,"learn_method_id":4,"level":0,"move_id":241},{"generation":4,"learn_method_id":4,"level":0,"move_id":249},{"generation":4,"learn_method_id":3,"level":0,"move_id":257},{"generation":4,"learn_method_id":4,"level":0,"move_id":259},{"generation":4,"learn_method_id":4,"level":0,"move_id":261},{"generation":4,"learn_method_id":4,"level":0,"move_id":263},{"generation":4,"learn_method_id":4,"level":0,"move_id":264},{"generation":4,"learn_method_id":1,"level":1,"move_id":269},{"generation":4,"learn_method_id":1,"level":9,"move_id":269},{"generation":4,"learn_method_id":4,"level":0,"move_id":269},{"generation":4,"learn_method_id":3,"level":0,"move_id":270},{"generation":4,"learn_method_id":3,"level":0,"move_id":272},{"generation":4,"learn_method_id":4,"level":0,"move_id":280},{"generation":4,"learn_method_id":3,"level":0,"move_id":283},{"generation":4,"learn_method_id":4,"level":0,"move_id":290},{"generation":4,"learn_method_id":3,"level":0,"move_id":307},{"generation":4,"learn_method_id":4,"level":0,"move_id":315},{"generation":4,"learn_method_id":4,"level":0,"move_id":317},{"generation":4,"learn_method_id":4,"level":0,"move_id":332},{"generation":4,"learn_method_id":4,"level":0,"move_id":339},{"generation":4,"learn_method_id":1,"level":53,"move_id":347},{"generation":4,"learn_method_id":4,"level":0,"move_id":347},{"generation":4,"learn_method_id":4,"level":0,"move_id":363},{"generation":4,"learn_method_id":1,"level":29,"move_id":364},{"generation":4,"learn_method_id":4,"level":0,"move_id":369},{"generation":4,"learn_method_id":1,"level":41,"move_id":370},{"generation":4,"learn_method_id":4,"level":0,"move_id":374},{"generation":4,"learn_method_id":1,"level":33,"move_id":386},{"generation":4,"learn_method_id":1,"level":57,"move_id":394},{"generation":4,"learn_method_id":4,"level":0,"move_id":398},{"generation":4,"learn_method_id":3,"level":0,"move_id":410},{"generation":4,"learn_method_id":4,"level":0,"move_id":411},{"generation":4,"learn_method_id":4,"level":0,"move_id":416},{"generation":4,"learn_method_id":4,"level":0,"move_id":421},{"generation":4,"learn_method_id":4,"level":0,"move_id":431},{"generation":4,"learn_method_id":3,"level":0,"move_id":441},{"generation":4,"learn_method_id":4,"level":0,"move_id":444},{"generation":4,"learn_method_id":4,"level":0,"move_id":445},{"generation":4,"learn_method_id":4,"level":0,"move_id":446},{"generation":4,"learn_method_id":4,"level":0,"move_id":447},{"generation":5,"learn_method_id":1,"level":1,"move_id":10},{"generation":5,"learn_method_id":4,"level":0,"move_id":14},{"generation":5,"learn_method_id":4,"level":0,"move_id":15},{"generation":5,"learn_method_id":1,"level":1,"move_id":43},{"generation":5,"learn_method_id":4,"level":0,"move_id":46},{"generation":5,"learn_method_id":1,"level":1,"move_id":52},{"generation":5,"learn_method_id":1,"level":7,"move_id":52},{"generation":5,"learn_method_id":4,"level":0,"move_id":53},{"generation":5,"learn_method_id":4,"level":0,"move_id":63},{"generation":5,"learn_method_id":4,"level":0,"move_id":70},{"generation":5,"learn_method_id":4,"level":0,"move_id":76},{"generation":5,"learn_method_id":1,"level":42,"move_id":83},{"generation":5,"learn_method_id":4,"level":0,"move_id":89},{"generation":5,"learn_method_id":4,"level":0,"move_id":91},{"generation":5,"learn_method_id":4,"level":0,"move_id":92},{"generation":5,"learn_method_id":4,"level":0,"move_id":104},{"generation":5,"learn_method_id":4,"level":0,"move_id":126},{"generation":5,"learn_method_id":1,"level":16,"move_id":154},{"generation":5,"learn_method_id":4,"level":0,"move_id":156},{"generation":5,"learn_method_id":4,"level":0,"move_id":157},{"generation":5,"learn_method_id":4,"level":0,"move_id":164},{"generation":5,"learn_method_id":1,"level":19,"move_id":172},{"generation":5,"learn_method_id":4,"level":0,"move_id":182},{"generation":5,"learn_method_id":1,"level":14,"move_id":183},{"generation":5,"learn_method_id":4,"level":0,"move_id":207},{"generation":5,"learn_method_id":4,"level":0,"move_id":213},{"generation":5,"learn_method_id":4,"level":0,"move_id":216},{"generation":5,"learn_method_id":4,"level":0,"move_id":218},{"generation":5,"learn_method_id":4,"level":0,"move_id":237},{"generation":5,"learn_method_id":4,"level":0,"move_id":241},{"generation":5,"learn_method_id":4,"level":0,"move_id":249},{"generation":5,"learn_method_id":4,"level":0,"move_id":259},{"generation":5,"learn_method_id":4,"level":0,"move_id":261},{"generation":5,"learn_method_id":4,"level":0,"move_id":263},{"generation":5,"learn_method_id":1,"level":1,"move_id":269},{"generation":5,"learn_method_id":1,"level":9,"move_id":269},{"generation":5,"learn_method_id":4,"level":0,"move_id":269},{"generation":5,"learn_method_id":4,"level":0,"move_id":280},{"generation":5,"learn_method_id":3,"level":0,"move_id":307},{"generation":5,"learn_method_id":4,"level":0,"move_id":315},{"generation":5,"learn_method_id":4,"level":0,"move_id":317},{"generation":5,"learn_method_id":4,"level":0,"move_id":332},{"generation":5,"learn_method_id":4,"level":0,"move_id":339},{"generation":5,"learn_method_id":1,"level":58,"move_id":347},{"generation":5,"learn_method_id":4,"level":0,"move_id":347},{"generation":5,"learn_method_id":1,"level":26,"move_id":364},{"generation":5,"learn_method_id":4,"level":0,"move_id":369},{"generation":5,"learn_method_id":1,"level":36,"move_id":370},{"generation":5,"learn_method_id":4,"level":0,"move_id":374},{"generation":5,"learn_method_id":1,"level":29,"move_id":386},{"generation":5,"learn_method_id":1,"level":68,"move_id":394},{"generation":5,"learn_method_id":4,"level":0,"move_id":398},{"generation":5,"learn_method_id":4,"level":0,"move_id":411},{"generation":5,"learn_method_id":4,"level":0,"move_id":416},{"generation":5,"learn_method_id":4,"level":0,"move_id":421},{"generation":5,"learn_method_id":4,"level":0,"move_id":444},{"generation":5,"learn_method_id":4,"level":0,"move_id":447},{"generation":5,"learn_method_id":4,"level":0,"move_id":468},{"generation":5,"learn_method_id":4,"level":0,"move_id":488},{"generation":5,"learn_method_id":4,"level":0,"move_id":490},{"generation":5,"learn_method_id":4,"level":0,"move_id":496},{"generation":5,"learn_method_id":4,"level":0,"move_id":510},{"generation":5,"learn_method_id":1,"level":52,"move_id":512},{"generation":5,"learn_method_id":4,"level":0,"move_id":512},{"generation":5,"learn_method_id":4,"level":0,"move_id":514},{"generation":5,"learn_method_id":3,"level":0,"move_id":519},{"generation":5,"learn_method_id":4,"level":0,"move_id":523},{"generation":5,"learn_method_id":4,"level":0,"move_id":526},{"generation":5,"learn_method_id":3,"level":0,"move_id":7},{"generation":5,"learn_method_id":3,"level":0,"move_id":9},{"generation":5,"learn_method_id":1,"level":1,"move_id":10},{"generation":5,"learn_method_id":4,"level":0,"move_id":14},{"generation":5,"learn_method_id":4,"level":0,"move_id":15},{"generation":5,"learn_method_id":1,"level":1,"move_id":43},{"generation":5,"learn_method_id":4,"level":0,"move_id":46},{"generation":5,"learn_method_id":1,"level":1,"move_id":52},{"generation":5,"learn_method_id":1,"level":7,"move_id":52},{"generation":5,"learn_method_id":4,"level":0,"move_id":53},{"generation":5,"learn_method_id":4,"level":0,"move_id":63},{"generation":5,"learn_method_id":3,"level":0,"move_id":67},{"generation":5,"learn_method_id":4,"level":0,"move_id":70},{"generation":5,"learn_method_id":4,"level":0,"move_id":76},{"generation":5,"learn_method_id":1,"level":42,"move_id":83},{"generation":5,"learn_method_id":4,"level":0,"move_id":89},{"generation":5,"learn_method_id":4,"level":0,"move_id":91},{"generation":5,"learn_method_id":4,"level":0,"move_id":92},{"generation":5,"learn_method_id":4,"level":0,"move_id":104},{"generation":5,"learn_method_id":4,"level":0,"move_id":126},{"generation":5,"learn_method_id":1,"level":16,"move_id":154},{"generation":5,"learn_method_id":4,"level":0,"move_id":156},{"generation":5,"learn_method_id":4,"level":0,"move_id":157},{"generation":5,"learn_method_id":4,"level":0,"move_id":164},{"generation":5,"learn_method_id":1,"level":19,"move_id":172},{"generation":5,"learn_method_id":3,"level":0,"move_id":173},{"generation":5,"learn_method_id":4,"level":0,"move_id":182},{"generation":5,"learn_method_id":1,"level":14,"move_id":183},{"generation":5,"learn_method_id":4,"level":0,"move_id":207},{"generation":5,"learn_method_id":4,"level":0,"move_id":213},{"generation":5,"learn_method_id":3,"level":0,"move_id":214},{"generation":5,"learn_method_id":4,"level":0,"move_id":216},{"generation":5,"learn_method_id":4,"level":0,"move_id":218},{"generation":5,"learn_method_id":3,"level":0,"move_id":231},{"generation":5,"learn_method_id":4,"level":0,"move_id":237},{"generation":5,"learn_method_id":4,"level":0,"move_id":241},{"generation":5,"learn_method_id":4,"level":0,"move_id":249},{"generation":5,"learn_method_id":3,"level":0,"move_id":257},{"generation":5,"learn_method_id":4,"level":0,"move_id":259},{"generation":5,"learn_method_id":4,"level":0,"move_id":261},{"generation":5,"learn_method_id":4,"level":0,"move_id":263},{"generation":5,"learn_method_id":1,"level":1,"move_id":269},{"generation":5,"learn_method_id":1,"level":9,"move_id":269},{"generation":5,"learn_method_id":4,"level":0,"move_id":269},{"generation":5,"learn_method_id":3,"level":0,"move_id":270},{"generation":5,"learn_method_id":3,"level":0,"move_id":272},{"generation":5,"learn_method_id":4,"level":0,"move_id":280},{"generation":5,"learn_method_id":3,"level":0,"move_id":283},{"generation":5,"learn_method_id":3,"level":0,"move_id":307},{"generation":5,"learn_method_id":4,"level":0,"move_id":315},{"generation":5,"learn_method_id":4,"level":0,"move_id":317},{"generation":5,"learn_method_id":4,"level":0,"move_id":332},{"generation":5,"learn_method_id":4,"level":0,"move_id":339},{"generation":5,"learn_method_id":3,"level":0,"move_id":343},{"generation":5,"learn_method_id":1,"level":58,"move_id":347},{"generation":5,"learn_method_id":4,"level":0,"move_id":347},{"generation":5,"learn_method_id":1,"level":26,"move_id":364},{"generation":5,"learn_method_id":4,"level":0,"move_id":369},{"generation":5,"learn_method_id":1,"level":36,"move_id":370},{"generation":5,"learn_method_id":4,"level":0,"move_id":374},{"generation":5,"learn_method_id":1,"level":29,"move_id":386},{"generation":5,"learn_method_id":1,"level":68,"move_id":394},{"generation":5,"learn_method_id":4,"level":0,"move_id":398},{"generation":5,"learn_method_id":4,"level":0,"move_id":411},{"generation":5,"learn_method_id":4,"level":0,"move_id":416},{"generation":5,"learn_method_id":4,"level":0,"move_id":421},{"generation":5,"learn_method_id":3,"level":0,"move_id":441},{"generation":5,"learn_method_id":4,"level":0,"move_id":444},{"generation":5,"learn_method_id":3,"level":0,"move_id":446},{"generation":5,"learn_method_id":4,"level":0,"move_id":447},{"generation":5,"learn_method_id":4,"level":0,"move_id":468},{"generation":5,"learn_method_id":4,"level":0,"move_id":488},{"generation":5,"learn_method_id":4,"level":0,"move_id":490},{"generation":5,"learn_method_id":4,"level":0,"move_id":496},{"generation":5,"learn_method_id":4,"level":0,"move_id":510},{"generation":5,"learn_method_id":1,"level":52,"move_id":512},{"generation":5,"learn_method_id":4,"level":0,"move_id":512},{"generation":5,"learn_method_id":4,"level":0,"move_id":514},{"generation":5,"learn_method_id":3,"level":0,"move_id":519},{"generation":5,"learn_method_id":4,"level":0,"move_id":523},{"generation":5,"learn_method_id":4,"level":0,"move_id":526},{"generation":5,"learn_method_id":3,"level":0,"move_id":530},{"generation":6,"learn_method_id":1,"level":1,"move_id":10},{"generation":6,"learn_method_id":4,"level":0,"move_id":14},{"generation":6,"learn_method_id":4,"level":0,"move_id":15},{"generation":6,"learn_method_id":1,"level":1,"move_id":43},{"generation":6,"learn_method_id":4,"level":0,"move_id":46},{"generation":6,"learn_method_id":1,"level":1,"move_id":52},{"generation":6,"learn_method_id":1,"level":7,"move_id":52},{"generation":6,"learn_method_id":4,"level":0,"move_id":53},{"generation":6,"learn_method_id":4,"level":0,"move_id":63},{"generation":6,"learn_method_id":4,"level":0,"move_id":70},{"generation":6,"learn_method_id":4,"level":0,"move_id":76},{"generation":6,"learn_method_id":1,"level":42,"move_id":83},{"generation":6,"learn_method_id":4,"level":0,"move_id":89},{"generation":6,"learn_method_id":4,"level":0,"move_id":91},{"generation":6,"learn_method_id":4,"level":0,"move_id":92},{"generation":6,"learn_method_id":4,"level":0,"move_id":104},{"generation":6,"learn_method_id":4,"level":0,"move_id":126},{"generation":6,"learn_method_id":1,"level":16,"move_id":154},{"generation":6,"learn_method_id":4,"level":0,"move_id":156},{"generation":6,"learn_method_id":4,"level":0,"move_id":157},{"generation":6,"learn_method_id":4,"level":0,"move_id":164},{"generation":6,"learn_method_id":1,"level":19,"move_id":172},{"generation":6,"learn_method_id":4,"level":0,"move_id":182},{"generation":6,"learn_method_id":1,"level":14,"move_id":183},{"generation":6,"learn_method_id":4,"level":0,"move_id":207},{"generation":6,"learn_method_id":4,"level":0,"move_id":213},{"generation":6,"learn_method_id":4,"level":0,"move_id":214},{"generation":6,"learn_method_id":4,"level":0,"move_id":216},{"generation":6,"learn_method_id":4,"level":0,"move_id":218},{"generation":6,"learn_method_id":4,"level":0,"move_id":237},{"generation":6,"learn_method_id":4,"level":0,"move_id":241},{"generation":6,"learn_method_id":4,"level":0,"move_id":249},{"generation":6,"learn_method_id":4,"level":0,"move_id":259},{"generation":6,"learn_method_id":4,"level":0,"move_id":261},{"generation":6,"learn_method_id":4,"level":0,"move_id":263},{"generation":6,"learn_method_id":1,"level":1,"move_id":269},{"generation":6,"learn_method_id":1,"level":9,"move_id":269},{"generation":6,"learn_method_id":4,"level":0,"move_id":269},{"generation":6,"learn_method_id":4,"level":0,"move_id":280},{"generation":6,"learn_method_id":3,"level":0,"move_id":307},{"generation":6,"learn_method_id":4,"level":0,"move_id":315},{"generation":6,"learn_method_id":4,"level":0,"move_id":317},{"generation":6,"learn_method_id":4,"level":0,"move_id":332},{"generation":6,"learn_method_id":4,"level":0,"move_id":339},{"generation":6,"learn_method_id":1,"level":58,"move_id":347},{"generation":6,"learn_method_id":4,"level":0,"move_id":347},{"generation":6,"learn_method_id":1,"level":26,"move_id":364},{"generation":6,"learn_method_id":4,"level":0,"move_id":369},{"generation":6,"learn_method_id":1,"level":36,"move_id":370},{"generation":6,"learn_method_id":4,"level":0,"move_id":374},{"generation":6,"learn_method_id":1,"level":29,"move_id":386},{"generation":6,"learn_method_id":1,"level":1,"move_id":394},{"generation":6,"learn_method_id":1,"level":68,"move_id":394},{"generation":6,"learn_method_id":4,"level":0,"move_id":398},{"generation":6,"learn_method_id":4,"level":0,"move_id":411},{"generation":6,"learn_method_id":4,"level":0,"move_id":416},{"generation":6,"learn_method_id":4,"level":0,"move_id":421},{"generation":6,"learn_method_id":4,"level":0,"move_id":444},{"generation":6,"learn_method_id":4,"level":0,"move_id":447},{"generation":6,"learn_method_id":4,"level":0,"move_id":468},{"generation":6,"learn_method_id":4,"level":0,"move_id":488},{"generation":6,"learn_method_id":4,"level":0,"move_id":490},{"generation":6,"learn_method_id":4,"level":0,"move_id":496},{"generation":6,"learn_method_id":4,"level":0,"move_id":510},{"generation":6,"learn_method_id":1,"level":52,"move_id":512},{"generation":6,"learn_method_id":4,"level":0,"move_id":512},{"generation":6,"learn_method_id":4,"level":0,"move_id":514},{"generation":6,"learn_method_id":3,"level":0,"move_id":519},{"generation":6,"learn_method_id":4,"level":0,"move_id":523},{"generation":6,"learn_method_id":4,"level":0,"move_id":590},{"generation":6,"learn_method_id":4,"level":0,"move_id":612},{"generation":6,"learn_method_id":3,"level":0,"move_id":7},{"generation":6,"learn_method_id":3,"level":0,"move_id":9},{"generation":6,"learn_method_id":1,"level":1,"move_id":10},{"generation":6,"learn_method_id":4,"level":0,"move_id":14},{"generation":6,"learn_method_id":4,"level":0,"move_id":15},{"generation":6,"learn_method_id":1,"level":1,"move_id":43},{"generation":6,"learn_method_id":4,"level":0,"move_id":46},{"generation":6,"learn_method_id":1,"level":1,"move_id":52},{"generation":6,"learn_method_id":1,"level":7,"move_id":52},{"generation":6,"learn_method_id":4,"level":0,"move_id":53},{"generation":6,"learn_method_id":4,"level":0,"move_id":63},{"generation":6,"learn_method_id":3,"level":0,"move_id":67},{"generation":6,"learn_method_id":4,"level":0,"move_id":70},{"generation":6,"learn_method_id":4,"level":0,"move_id":76},{"generation":6,"learn_method_id":1,"level":42,"move_id":83},{"generation":6,"learn_method_id":4,"level":0,"move_id":89},{"generation":6,"learn_method_id":4,"level":0,"move_id":91},{"generation":6,"learn_method_id":4,"level":0,"move_id":92},{"generation":6,"learn_method_id":4,"level":0,"move_id":104},{"generation":6,"learn_method_id":4,"level":0,"move_id":126},{"generation":6,"learn_method_id":1,"level":16,"move_id":154},{"generation":6,"learn_method_id":4,"level":0,"move_id":156},{"generation":6,"learn_method_id":4,"level":0,"move_id":157},{"generation":6,"learn_method_id":4,"level":0,"move_id":164},{"generation":6,"learn_method_id":1,"level":19,"move_id":172},{"generation":6,"learn_method_id":3,"level":0,"move_id":173},{"generation":6,"learn_method_id":4,"level":0,"move_id":182},{"generation":6,"learn_method_id":1,"level":14,"move_id":183},{"generation":6,"learn_method_id":4,"level":0,"move_id":207},{"generation":6,"learn_method_id":4,"level":0,"move_id":213},{"generation":6,"learn_method_id":4,"level":0,"move_id":214},{"generation":6,"learn_method_id":4,"level":0,"move_id":216},{"generation":6,"learn_method_id":4,"level":0,"move_id":218},{"generation":6,"learn_method_id":3,"level":0,"move_id":231},{"generation":6,"learn_method_id":4,"level":0,"move_id":237},{"generation":6,"learn_method_id":4,"level":0,"move_id":241},{"generation":6,"learn_method_id":4,"level":0,"move_id":249},{"generation":6,"learn_method_id":3,"level":0,"move_id":257},{"generation":6,"learn_method_id":4,"level":0,"move_id":259},{"generation":6,"learn_method_id":4,"level":0,"move_id":261},{"generation":6,"learn_method_id":4,"level":0,"move_id":263},{"generation":6,"learn_method_id":3,"level":0,"move_id":264},{"generation":6,"learn_method_id":1,"level":1,"move_id":269},{"generation":6,"learn_method_id":1,"level":9,"move_id":269},{"generation":6,"learn_method_id":4,"level":0,"move_id":269},{"generation":6,"learn_method_id":3,"level":0,"move_id":270},{"generation":6,"learn_method_id":3,"level":0,"move_id":272},{"generation":6,"learn_method_id":4,"level":0,"move_id":280},{"generation":6,"learn_method_id":3,"level":0,"move_id":283},{"generation":6,"learn_method_id":4,"level":0,"move_id":290},{"generation":6,"learn_method_id":3,"level":0,"move_id":307},{"generation":6,"learn_method_id":4,"level":0,"move_id":315},{"generation":6,"learn_method_id":4,"level":0,"move_id":317},{"generation":6,"learn_method_id":4,"level":0,"move_id":332},{"generation":6,"learn_method_id":4,"level":0,"move_id":339},{"generation":6,"learn_method_id":3,"level":0,"move_id":343},{"generation":6,"learn_method_id":1,"level":58,"move_id":347},{"generation":6,"learn_method_id":4,"level":0,"move_id":347},{"generation":6,"learn_method_id":1,"level":26,"move_id":364},{"generation":6,"learn_method_id":4,"level":0,"move_id":369},{"generation":6,"learn_method_id":1,"level":36,"move_id":370},{"generation":6,"learn_method_id":4,"level":0,"move_id":374},{"generation":6,"learn_method_id":1,"level":29,"move_id":386},{"generation":6,"learn_method_id":1,"level":1,"move_id":394},{"generation":6,"learn_method_id":1,"level":68,"move_id":394},{"generation":6,"learn_method_id":4,"level":0,"move_id":398},{"generation":6,"learn_method_id":4,"level":0,"move_id":411},{"generation":6,"learn_method_id":4,"level":0,"move_id":416},{"generation":6,"learn_method_id":4,"level":0,"move_id":421},{"generation":6,"learn_method_id":3,"level":0,"move_id":441},{"generation":6,"learn_method_id":4,"level":0,"move_id":444},{"generation":6,"learn_method_id":3,"level":0,"move_id":446},{"generation":6,"learn_method_id":4,"level":0,"move_id":447},{"generation":6,"learn_method_id":4,"level":0,"move_id":468},{"generation":6,"learn_method_id":4,"level":0,"move_id":488},{"generation":6,"learn_method_id":4,"level":0,"move_id":490},{"generation":6,"learn_method_id":4,"level":0,"move_id":496},{"generation":6,"learn_method_id":4,"level":0,"move_id":510},{"generation":6,"learn_method_id":1,"level":52,"move_id":512},{"generation":6,"learn_method_id":4,"level":0,"move_id":512},{"generation":6,"learn_method_id":4,"level":0,"move_id":514},{"generation":6,"learn_method_id":3,"level":0,"move_id":519},{"generation":6,"learn_method_id":4,"level":0,"move_id":523},{"generation":6,"learn_method_id":3,"level":0,"move_id":530},{"generation":6,"learn_method_id":4,"level":0,"move_id":590},{"generation":6,"learn_method_id":4,"level":0,"move_id":612},{"generation":7,"learn_method_id":1,"level":1,"move_id":10},{"generation":7,"learn_method_id":4,"level":0,"move_id":14},{"generation":7,"learn_method_id":1,"level":1,"move_id":43},{"generation":7,"learn_method_id":4,"level":0,"move_id":46},{"generation":7,"learn_method_id":1,"level":1,"move_id":52},{"generation":7,"learn_method_id":1,"level":7,"move_id":52},{"generation":7,"learn_method_id":4,"level":0,"move_id":53},{"generation":7,"learn_method_id":4,"level":0,"move_id":63},{"generation":7,"learn_method_id":4,"level":0,"move_id":76},{"generation":7,"learn_method_id":1,"level":42,"move_id":83},{"generation":7,"learn_method_id":4,"level":0,"move_id":89},{"generation":7,"learn_method_id":4,"level":0,"move_id":92},{"generation":7,"learn_method_id":4,"level":0,"move_id":104},{"generation":7,"learn_method_id":4,"level":0,"move_id":126},{"generation":7,"learn_method_id":1,"level":16,"move_id":154},{"generation":7,"learn_method_id":4,"level":0,"move_id":156},{"generation":7,"learn_method_id":4,"level":0,"move_id":157},{"generation":7,"learn_method_id":4,"level":0,"move_id":164},{"generation":7,"learn_method_id":1,"level":19,"move_id":172},{"generation":7,"learn_method_id":4,"level":0,"move_id":182},{"generation":7,"learn_method_id":1,"level":1,"move_id":183},{"generation":7,"learn_method_id":4,"level":0,"move_id":207},{"generation":7,"learn_method_id":4,"level":0,"move_id":213},{"generation":7,"learn_method_id":4,"level":0,"move_id":214},{"generation":7,"learn_method_id":4,"level":0,"move_id":216},{"generation":7,"learn_method_id":4,"level":0,"move_id":218},{"generation":7,"learn_method_id":4,"level":0,"move_id":237},{"generation":7,"learn_method_id":4,"level":0,"move_id":241},{"generation":7,"learn_method_id":4,"level":0,"move_id":259},{"generation":7,"learn_method_id":4,"level":0,"move_id":261},{"generation":7,"learn_method_id":4,"level":0,"move_id":263},{"generation":7,"learn_method_id":1,"level":1,"move_id":269},{"generation":7,"learn_method_id":1,"level":9,"move_id":269},{"generation":7,"learn_method_id":4,"level":0,"move_id":269},{"generation":7,"learn_method_id":4,"level":0,"move_id":280},{"generation":7,"learn_method_id":3,"level":0,"move_id":307},{"generation":7,"learn_method_id":4,"level":0,"move_id":315},{"generation":7,"learn_method_id":4,"level":0,"move_id":317},{"generation":7,"learn_method_id":4,"level":0,"move_id":332},{"generation":7,"learn_method_id":4,"level":0,"move_id":339},{"generation":7,"learn_method_id":1,"level":58,"move_id":347},{"generation":7,"learn_method_id":4,"level":0,"move_id":347},{"generation":7,"learn_method_id":1,"level":26,"move_id":364},{"generation":7,"learn_method_id":4,"level":0,"move_id":369},{"generation":7,"learn_method_id":1,"level":0,"move_id":370},{"generation":7,"learn_method_id":1,"level":1,"move_id":370},{"generation":7,"learn_method_id":4,"level":0,"move_id":374},{"generation":7,"learn_method_id":1,"level":29,"move_id":386},{"generation":7,"learn_method_id":1,"level":1,"move_id":394},{"generation":7,"learn_method_id":1,"level":68,"move_id":394},{"generation":7,"learn_method_id":4,"level":0,"move_id":398},{"generation":7,"learn_method_id":4,"level":0,"move_id":411},{"generation":7,"learn_method_id":4,"level":0,"move_id":416},{"generation":7,"learn_method_id":4,"level":0,"move_id":421},{"generation":7,"learn_method_id":4,"level":0,"move_id":444},{"generation":7,"learn_method_id":4,"level":0,"move_id":447},{"generation":7,"learn_method_id":4,"level":0,"move_id":488},{"generation":7,"learn_method_id":4,"level":0,"move_id":490},{"generation":7,"learn_method_id":4,"level":0,"move_id":496},{"generation":7,"learn_method_id":1,"level":52,"move_id":512},{"generation":7,"learn_method_id":4,"level":0,"move_id":512},{"generation":7,"learn_method_id":3,"level":0,"move_id":519},{"generation":7,"learn_method_id":4,"level":0,"move_id":523},{"generation":7,"learn_method_id":4,"level":0,"move_id":526},{"generation":7,"learn_method_id":4,"level":0,"move_id":590},{"generation":7,"learn_method_id":3,"level":0,"move_id":7},{"generation":7,"learn_method_id":3,"level":0,"move_id":9},{"generation":7,"learn_method_id":1,"level":1,"move_id":10},{"generation":7,"learn_method_id":4,"level":0,"move_id":14},{"generation":7,"learn_method_id":1,"level":1,"move_id":43},{"generation":7,"learn_method_id":4,"level":0,"move_id":46},{"generation":7,"learn_method_id":1,"level":1,"move_id":52},{"generation":7,"learn_method_id":1,"level":7,"move_id":52},{"generation":7,"learn_method_id":4,"level":0,"move_id":53},{"generation":7,"learn_method_id":4,"level":0,"move_id":63},{"generation":7,"learn_method_id":3,"level":0,"move_id":67},{"generation":7,"learn_method_id":4,"level":0,"move_id":76},{"generation":7,"learn_method_id":1,"level":42,"move_id":83},{"generation":7,"learn_method_id":4,"level":0,"move_id":89},{"generation":7,"learn_method_id":4,"level":0,"move_id":92},{"generation":7,"learn_method_id":4,"level":0,"move_id":104},{"generation":7,"learn_method_id":4,"level":0,"move_id":126},{"generation":7,"learn_method_id":1,"level":16,"move_id":154},{"generation":7,"learn_method_id":4,"level":0,"move_id":156},{"generation":7,"learn_method_id":4,"level":0,"move_id":157},{"generation":7,"learn_method_id":4,"level":0,"move_id":164},{"generation":7,"learn_method_id":1,"level":19,"move_id":172},{"generation":7,"learn_method_id":3,"level":0,"move_id":173},{"generation":7,"learn_method_id":4,"level":0,"move_id":182},{"generation":7,"learn_method_id":1,"level":1,"move_id":183},{"generation":7,"learn_method_id":4,"level":0,"move_id":207},{"generation":7,"learn_method_id":4,"level":0,"move_id":213},{"generation":7,"learn_method_id":4,"level":0,"move_id":214},{"generation":7,"learn_method_id":4,"level":0,"move_id":216},{"generation":7,"learn_method_id":4,"level":0,"move_id":218},{"generation":7,"learn_method_id":3,"level":0,"move_id":231},{"generation":7,"learn_method_id":4,"level":0,"move_id":237},{"generation":7,"learn_method_id":4,"level":0,"move_id":241},{"generation":7,"learn_method_id":3,"level":0,"move_id":257},{"generation":7,"learn_method_id":4,"level":0,"move_id":259},{"generation":7,"learn_method_id":4,"level":0,"move_id":261},{"generation":7,"learn_method_id":4,"level":0,"move_id":263},{"generation":7,"learn_method_id":3,"level":0,"move_id":264},{"generation":7,"learn_method_id":1,"level":1,"move_id":269},{"generation":7,"learn_method_id":1,"level":9,"move_id":269},{"generation":7,"learn_method_id":4,"level":0,"move_id":269},{"generation":7,"learn_method_id":3,"level":0,"move_id":270},{"generation":7,"learn_method_id":3,"level":0,"move_id":272},{"generation":7,"learn_method_id":4,"level":0,"move_id":280},{"generation":7,"learn_method_id":3,"level":0,"move_id":283},{"generation":7,"learn_method_id":3,"level":0,"move_id":307},{"generation":7,"learn_method_id":4,"level":0,"move_id":315},{"generation":7,"learn_method_id":4,"level":0,"move_id":317},{"generation":7,"learn_method_id":4,"level":0,"move_id":332},{"generation":7,"learn_method_id":4,"level":0,"move_id":339},{"generation":7,"learn_method_id":3,"level":0,"move_id":343},{"generation":7,"learn_method_id":1,"level":58,"move_id":347},{"generation":7,"learn_method_id":4,"level":0,"move_id":347},{"generation":7,"learn_method_id":1,"level":26,"move_id":364},{"generation":7,"learn_method_id":4,"level":0,"move_id":369},{"generation":7,"learn_method_id":1,"level":0,"move_id":370},{"generation":7,"learn_method_id":1,"level":1,"move_id":370},{"generation":7,"learn_method_id":4,"level":0,"move_id":374},{"generation":7,"learn_method_id":1,"level":29,"move_id":386},{"generation":7,"learn_method_id":1,"level":1,"move_id":394},{"generation":7,"learn_method_id":1,"level":68,"move_id":394},{"generation":7,"learn_method_id":4,"level":0,"move_id":398},{"generation":7,"learn_method_id":4,"level":0,"move_id":411},{"generation":7,"learn_method_id":4,"level":0,"move_id":416},{"generation":7,"learn_method_id":4,"level":0,"move_id":421},{"generation":7,"learn_method_id":3,"level":0,"move_id":441},{"generation":7,"learn_method_id":4,"level":0,"move_id":444},{"generation":7,"learn_method_id":3,"level":0,"move_id":446},{"generation":7,"learn_method_id":4,"level":0,"move_id":447},{"generation":7,"learn_method_id":4,"level":0,"move_id":488},{"generation":7,"learn_method_id":4,"level":0,"move_id":490},{"generation":7,"learn_method_id":4,"level":0,"move_id":496},{"generation":7,"learn_method_id":1,"level":52,"move_id":512},{"generation":7,"learn_method_id":4,"level":0,"move_id":512},{"generation":7,"learn_method_id":3,"level":0,"move_id":519},{"generation":7,"learn_method_id":4,"level":0,"move_id":523},{"generation":7,"learn_method_id":4,"level":0,"move_id":526},{"generation":7,"learn_method_id":3,"level":0,"move_id":530},{"generation":7,"learn_method_id":4,"level":0,"move_id":590},{"generation":7,"learn_method_id":3,"level":0,"move_id":673}]}