{"id":664,"genderRate":4,"captureRate":255,"baseHappiness":70,"legendary":false,"mythical":false,"abilities":[{"hidden":false,"id":14},{"hidden":false,"id":19},{"hidden":true,"id":132}],"stats":[{"id":1,"base":38,"effort":0},{"id":2,"base":35,"effort":0},{"id":3,"base":40,"effort":1},{"id":4,"base":27,"effort":0},{"id":5,"base":25,"effort":0},{"id":6,"base":35,"effort":0}],"moves":[{"generation":6,"learn_method_id":1,"level":1,"move_id":33},{"generation":6,"learn_method_id":1,"level":1,"move_id":81},{"generation":6,"learn_method_id":1,"level":6,"move_id":78},{"generation":6,"learn_method_id":1,"level":15,"move_id":450},{"generation":6,"learn_method_id":2,"level":0,"move_id":77},{"generation":6,"learn_method_id":2,"level":0,"move_id":78},{"generation":6,"learn_method_id":2,"level":0,"move_id":476},{"generation":6,"learn_method_id":3,"level":0,"move_id":450},{"generation":7,"learn_method_id":1,"level":1,"move_id":33},{"generation":7,"learn_method_id":1,"level":1,"move_id":81},{"generation":7,"learn_method_id":1,"level":6,"move_id":78},{"generation":7,"learn_method_id":1,"level":15,"move_id":450},{"generation":7,"learn_method_id":2,"level":0,"move_id":77},{"generation":7,"learn_method_id":2,"level":0,"move_id":78},{"generation":7,"learn_method_id":2,"level":0,"move_id":476},{"generation":7,"learn_method_id":3,"level":0,"move_id":450},{"generation":9,"learn_method_id":1,"level":1,"move_id":33},{"generation":9,"learn_method_id":1,"level":1,"move_id":81},{"generation":9,"learn_method_id":1,"level":6,"move_id":78},{"generation":9,"learn_method_id":1,"level":15,"move_id":450},{"generation":9,"learn_method_id":2,"level":0,"move_id":77},{"generation":9,"learn_method_id":2,"level":0,"move_id":476},{"generation":9,"learn_method_id":4,"level":0,"move_id":522},{"generation":9,"learn_method_id":4,"level":0,"move_id":851},{"generation":9,"learn_method_id":4,"level":0,"move_id":884},{"generation":9,"learn_method_id":4,"level":0,"move_id":450}]}