{"id":815,"genderRate":1,"captureRate":45,"baseHappiness":50,"legendary":false,"mythical":false,"abilities":[{"hidden":false,"id":66},{"hidden":true,"id":236}],"stats":[{"id":1,"base":80,"effort":0},{"id":2,"base":116,"effort":0},{"id":3,"base":75,"effort":0},{"id":4,"base":65,"effort":0},{"id":5,"base":75,"effort":0},{"id":6,"base":119,"effort":3}],"moves":[{"generation":8,"learn_method_id":4,"level":0,"move_id":7},{"generation":8,"learn_method_id":1,"level":12,"move_id":24},{"generation":8,"learn_method_id":4,"level":0,"move_id":25},{"generation":8,"learn_method_id":1,"level":30,"move_id":29},{"generation":8,"learn_method_id":1,"level":1,"move_id":33},{"generation":8,"learn_method_id":1,"level":54,"move_id":38},{"generation":8,"learn_method_id":1,"level":1,"move_id":45},{"generation":8,"learn_method_id":1,"level":1,"move_id":52},{"generation":8,"learn_method_id":4,"level":0,"move_id":53},{"generation":8,"learn_method_id":4,"level":0,"move_id":63},{"generation":8,"learn_method_id":4,"level":0,"move_id":67},{"generation":8,"learn_method_id":1,"level":38,"move_id":68},{"generation":8,"learn_method_id":4,"level":0,"move_id":83},{"generation":8,"learn_method_id":1,"level":24,"move_id":97},{"generation":8,"learn_method_id":4,"level":0,"move_id":97},{"generation":8,"learn_method_id":1,"level":1,"move_id":98},{"generation":8,"learn_method_id":4,"level":0,"move_id":116},{"generation":8,"learn_method_id":4,"level":0,"move_id":126},{"generation":8,"learn_method_id":4,"level":0,"move_id":129},{"generation":8,"learn_method_id":4,"level":0,"move_id":156},{"generation":8,"learn_method_id":4,"level":0,"move_id":164},{"generation":8,"learn_method_id":4,"level":0,"move_id":173},{"generation":8,"learn_method_id":4,"level":0,"move_id":179},{"generation":8,"learn_method_id":4,"level":0,"move_id":182},{"generation":8,"learn_method_id":4,"level":0,"move_id":203},{"generation":8,"learn_method_id":4,"level":0,"move_id":213},{"generation":8,"learn_method_id":4,"level":0,"move_id":214},{"generation":8,"learn_method_id":4,"level":0,"move_id":226},{"generation":8,"learn_method_id":4,"level":0,"move_id":241},{"generation":8,"learn_method_id":4,"level":0,"move_id":247},{"generation":8,"learn_method_id":4,"level":0,"move_id":257},{"generation":8,"learn_method_id":4,"level":0,"move_id":263},{"generation":8,"learn_method_id":4,"level":0,"move_id":269},{"generation":8,"learn_method_id":4,"level":0,"move_id":270},{"generation":8,"learn_method_id":4,"level":0,"move_id":279},{"generation":8,"learn_method_id":4,"level":0,"move_id":299},{"generation":8,"learn_method_id":3,"level":0,"move_id":307},{"generation":8,"learn_method_id":4,"level":0,"move_id":315},{"generation":8,"learn_method_id":4,"level":0,"move_id":339},{"generation":8,"learn_method_id":1,"level":46,"move_id":340},{"generation":8,"learn_method_id":4,"level":0,"move_id":340},{"generation":8,"learn_method_id":4,"level":0,"move_id":341},{"generation":8,"learn_method_id":1,"level":1,"move_id":364},{"generation":8,"learn_method_id":4,"level":0,"move_id":369},{"generation":8,"learn_method_id":4,"level":0,"move_id":372},{"generation":8,"learn_method_id":4,"level":0,"move_id":394},{"generation":8,"learn_method_id":4,"level":0,"move_id":411},{"generation":8,"learn_method_id":4,"level":0,"move_id":416},{"generation":8,"learn_method_id":4,"level":0,"move_id":424},{"generation":8,"learn_method_id":4,"level":0,"move_id":428},{"generation":8,"learn_method_id":4,"level":0,"move_id":441},{"generation":8,"learn_method_id":4,"level":0,"move_id":442},{"generation":8,"learn_method_id":4,"level":0,"move_id":486},{"generation":8,"learn_method_id":1,"level":19,"move_id":488},{"generation":8,"learn_method_id":4,"level":0,"move_id":490},{"generation":8,"learn_method_id":4,"level":0,"move_id":496},{"generation":8,"learn_method_id":4,"level":0,"move_id":502},{"generation":8,"learn_method_id":4,"level":0,"move_id":512},{"generation":8,"learn_method_id":3,"level":0,"move_id":519},{"generation":8,"learn_method_id":4,"level":0,"move_id":526},{"generation":8,"learn_method_id":4,"level":0,"move_id":555},{"generation":8,"learn_method_id":1,"level":62,"move_id":756},{"generation":8,"learn_method_id":1,"level":0,"move_id":780},{"generation":8,"learn_method_id":1,"level":1,"move_id":780},{"generation":8,"learn_method_id":3,"level":0,"move_id":811},{"generation":8,"learn_method_id":3,"level":0,"move_id":815}]}